django_snappy_vumi_bouncer-0.2.0.dist-info/DESCRIPTION.rst
django_snappy_vumi_bouncer-0.2.0.dist-info/METADATA
django_snappy_vumi_bouncer-0.2.0.dist-info/metadata.json
django_snappy_vumi_bouncer-0.2.0.dist-info/RECORD
django_snappy_vumi_bouncer-0.2.0.dist-info/top_level.txt
django_snappy_vumi_bouncer-0.2.0.dist-info/WHEEL
snappybouncer/__init__.py
snappybouncer/actions.py
snappybouncer/admin.py
snappybouncer/api.py
snappybouncer/models.py
snappybouncer/tasks.py
snappybouncer/tests.py
snappybouncer/urls.py
snappybouncer/views.py
snappybouncer/migrations/0001_initial.py
snappybouncer/migrations/__init__.py
snappybouncer/tests/__init__.py
snappybouncer/tests/helpers.py
snappybouncer/tests/test_api.py
