Metadata-Version: 2.0
Name: django-snappy-vumi-bouncer
Version: 0.2.0
Summary: A Django app that bounces messages from Vumi to Snappy and back
Home-page: https://github.com/westerncapelabs/django-snappy-vumi-bouncer
Author: Western Cap Labs
Author-email: devops@westerncapelabs.com
License: BSD
Platform: UNKNOWN
Classifier: Development Status :: 4 - Beta
Classifier: Intended Audience :: Developers
Classifier: License :: OSI Approved :: BSD License
Classifier: Operating System :: POSIX
Classifier: Programming Language :: Python
Classifier: Topic :: Software Development :: Libraries :: Python Modules
Classifier: Topic :: System :: Networking
Requires-Dist: Django
Requires-Dist: django-tastypie
Requires-Dist: besnappy
Requires-Dist: django-celery
Requires-Dist: go-http
Requires-Dist: South
